{"id": "c1904b92-deac-4171-8144-9362935e2097", "url": "https://www.carismaslimming.com/blog/everything-you-need-to-know-about-dermal-fillers", "slug": "everything-you-need-to-know-about-dermal-fillers", "title": "Everything You Need to Know About Dermal Fillers", "published_date": "2025-02-01T15:00:24.658Z", "last_updated": "2025-02-12T10:07:16.764Z", "minutes_to_read": 4, "excerpt": "In the world of aesthetic treatments, dermal fillers  have become one of the most popular and effective solutions for restoring youthful...", "cover_image_url": "https://static.wixstatic.com/media/f940f0_a177c7f571314973b33c44ac4f2f2126~mv2.jpg/v1/fill/w_800,h_500,al_c,q_85,enc_auto/f940f0_a177c7f571314973b33c44ac4f2f2126~mv2.jpg", "body_text": "In the world of aesthetic treatments, dermal fillers have become one of the most popular and effective solutions for restoring youthful volume, smoothing wrinkles, and enhancing facial features. Whether you’re looking to rejuvenate your appearance, enhance your lips, or soften deep lines, dermal fillers can provide a non-surgical way to achieve a refreshed, natural look. If you’re considering dermal fillers, understanding the benefits, process, and results is key to making an informed decision.\n\nIn this guide, we’ll explore everything you need to know about dermal fillers, from how they work to the types available and the results you can expect. Let’s dive into the world of dermal fillers and how they can help you look and feel your best.\n\n[Image: Dermal Filler]\n\n1. What Are Dermal Fillers?\nDermal fillers are injectable treatments used to restore volume, smooth wrinkles, and enhance facial contours. They are made of various substances, with the most common being hyaluronic acid, a naturally occurring substance in the body that helps retain moisture and plump the skin. Other types of fillers include calcium hydroxylapatite, poly-L-lactic acid, and autologous fat (fat derived from your own body). Each type of filler serves different purposes, depending on the area being treated and the desired outcome.\n\nThe primary function of dermal fillers is to replenish lost volume in the face, which can occur due to aging or lifestyle factors. As we age, the skin loses collagen and elasticity, causing it to sag and develop wrinkles. Dermal fillers work by adding volume to the skin, helping to lift and smooth out wrinkles, restore facial contours, and enhance features such as the cheeks, lips, and jawline. The results are typically immediate and can last from several months to over a year, depending on the type of filler used.\n\n\n2. The Benefits of Dermal Fillers\nDermal fillers offer a range of benefits, making them a popular choice for individuals seeking non-surgical aesthetic enhancements. Here are some of the key advantages of dermal fillers:\nRestores Volume and Youthful Contours: As we age, we naturally lose volume in certain areas of the face, such as the cheeks, temples, and under the eyes. Dermal fillers help restore this lost volume, giving the face a more youthful, lifted appearance.\n\nSmooths Wrinkles and Fine Lines: Dermal fillers are highly effective at softening wrinkles, fine lines, and folds, particularly around the mouth, nose, and forehead. By filling in these lines, fillers create a smoother, more even skin surface.\n\nEnhances Facial Features: Fillers can be used to enhance specific facial features, such as the lips, chin, and jawline. Whether you want fuller lips, a more defined jawline, or a more sculpted nose, dermal fillers can provide subtle, natural-looking enhancements.\n\nNon-Surgical and Minimal Downtime: One of the biggest advantages of dermal fillers is that they are non-invasive treatments, meaning there is no need for surgery or lengthy recovery periods. Most people can resume normal activities immediately after the procedure, with only minor swelling or bruising as potential side effects.\n\nCustomizable Results: Dermal fillers can be tailored to your individual needs. Whether you want to target specific wrinkles or enhance certain facial features, the treatment can be customized to achieve your desired results.\n\n\n\n3. The Dermal Filler Process\nThe dermal filler procedure is relatively quick and straightforward, typically taking between 15 and 30 minutes, depending on the number of areas being treated. Here’s a step-by-step breakdown of the process:\nConsultation: Before the treatment, you’ll have a consultation with a qualified practitioner who will assess your skin, discuss your aesthetic goals, and recommend the best filler for your needs. The practitioner will also explain the procedure, risks, and expected results.\n\nPreparation: On the day of the treatment, the targeted areas will be cleansed and, if necessary, a topical numbing cream will be applied to minimize discomfort. Some dermal fillers also contain a local anesthetic to enhance comfort during the procedure.\n\nInjection: The practitioner will use a fine needle to inject the dermal filler into the targeted areas of your face. The process is generally well-tolerated, and most patients report only mild discomfort.\n\nPost-Treatment Care: After the procedure, you may experience some swelling, bruising, or redness at the injection sites. These side effects are usually temporary and subside within a few days. The practitioner will provide aftercare instructions, which may include avoiding excessive sun exposure and strenuous activities for a short period.\n\n\n\n4. What to Expect from Dermal Filler Results\nThe results of dermal fillers are usually visible immediately after the treatment, with some improvements becoming more apparent as any swelling subsides. For example, after a lip filler treatment, you may notice fuller lips right away, while cheek fillers can give your face a more youthful, lifted appearance. However, the final results will become more evident over the next few days as the filler settles into place.\n\nThe longevity of dermal fillers varies depending on the type of filler used and the area treated. Hyaluronic acid-based fillers typically last between 6 to 12 months, while other types of fillers, such as those made with poly-L-lactic acid or calcium hydroxylapatite, may last longer. Maintenance treatments may be necessary to sustain the results, but dermal fillers offer long-lasting benefits with minimal upkeep.\n\n\n5. Are Dermal Fillers Safe?\nDermal fillers are generally considered safe when performed by a qualified and experienced practitioner. However, as with any cosmetic procedure, there are some risks involved. The most common side effects include mild swelling, bruising, and redness at the injection sites, which typically resolve within a few days. In rare cases, more serious complications can occur, such as infection or allergic reactions, but these are uncommon when the procedure is performed by a trained professional.\n\nTo ensure safety and optimal results, it’s important to choose a reputable clinic with experienced practitioners who use high-quality, FDA-approved fillers. During your consultation, ask questions about the practitioner’s experience, the type of filler being used, and the expected outcomes.\n\n\nDermal Fillers for a Youthful, Refreshed Look\nDermal fillers offer a safe, effective, and non-invasive solution for those looking to restore volume, smooth wrinkles, and enhance their facial features. Whether you’re interested in rejuvenating your appearance, reducing fine lines, or achieving fuller lips, dermal fillers can help you achieve your aesthetic goals with minimal downtime and long-lasting results.\n\nIf you're considering dermal fillers, book a free consultation at Carisma Aesthetics to learn more about the treatment options that are best suited for you. Our expert team will guide you through the process and help you achieve natural, youthful results.", "body_image_urls": ["https://static.wixstatic.com/media/f940f0_a177c7f571314973b33c44ac4f2f2126~mv2.jpg/v1/fill/w_800,h_500,al_c,q_85,enc_auto/f940f0_a177c7f571314973b33c44ac4f2f2126~mv2.jpg"], "categories": [], "tags": [], "wix_post_id": "c1904b92-deac-4171-8144-9362935e2097"}